deflemask_preset_viewer/__init__.py
deflemask_preset_viewer/__main__.py
deflemask_preset_viewer/code.py
deflemask_preset_viewer/fm_operator.py
deflemask_preset_viewer/main.py
deflemask_preset_viewer/preset.py
deflemask_preset_viewer/ui.py
deflemask_preset_viewer/util.py
deflemask_preset_viewer/dmp/__init__.py
deflemask_preset_viewer/dmp/dmp.py
deflemask_preset_viewer/dmp/dmp_parser.py
deflemask_preset_viewer/tfi/__init__.py
deflemask_preset_viewer/tfi/tfi.py
deflemask_preset_viewer/tfi/tfi_parser.py
deflemask_preset_viewer/wopn/__init__.py
deflemask_preset_viewer/wopn/wopn.py
deflemask_preset_viewer/wopn/wopn_bank.py
deflemask_preset_viewer/wopn/wopn_instrument.py
deflemask_preset_viewer/wopn/wopn_parser.py
deflemask_preset_viewer-0.7.0.dist-info/licenses/LICENSE
deflemask_preset_viewer-0.7.0.dist-info/METADATA
deflemask_preset_viewer-0.7.0.dist-info/WHEEL
deflemask_preset_viewer-0.7.0.dist-info/entry_points.txt
deflemask_preset_viewer-0.7.0.dist-info/top_level.txt
deflemask_preset_viewer-0.7.0.dist-info/RECORD
