Metadata-Version: 2.4
Name: deflemask-preset-viewer
Version: 0.7.0
Summary: Reads and outputs FM parameters contained within DefleMask's DMP files as well as libOPNMIDI WOPN files
Home-page: https://github.com/rhargreaves/deflemask-preset-viewer
Author: Robert Hargreaves
Author-email: python-package@roberthargreaves.net
Project-URL: Bug Tracker, https://github.com/rhargreaves/deflemask-preset-viewer/issues
Project-URL: Source Code, https://github.com/rhargreaves/deflemask-preset-viewer
Classifier: Programming Language :: Python :: 3.12
Classifier: Topic :: Multimedia :: Sound/Audio
Classifier: License :: OSI Approved :: MIT License
Classifier: Operating System :: OS Independent
Requires-Python: >=3.12
License-File: LICENSE
Dynamic: author
Dynamic: author-email
Dynamic: classifier
Dynamic: description
Dynamic: description-content-type
Dynamic: home-page
Dynamic: license-file
Dynamic: project-url
Dynamic: requires-python
Dynamic: summary
